cs223-2.srcs/sources_1/new/full_substractor_test.sv
`timescale 1ns / 1ps
//////////////////////////////////////////////////////////////////////////////////
// Company: 
// Engineer: 
// 
// Create Date: 10.03.2024 16:07:04
// Design Name: 
// Module Name: full_substractor_test
// Project Name: 
// Target Devices: 
// Tool Versions: 
// Description: 
// 
// Dependencies: 
// 
// Revision:
// Revision 0.01 - File Created
// Additional Comments:
// 
//////////////////////////////////////////////////////////////////////////////////


module XOR2 (
  input logic a,
  input logic b,
  output logic y
);
  assign y = a ^ b;
endmodule

module AND2 (
  input logic a,
  input logic b,
  output logic y
);
  assign y = a & b;
endmodule

module OR2 (
  input logic a,
  input logic b,
  output logic y
);
  assign y = a | b;
endmodule

module full_substractor_test (
  input logic A,
  input logic B,
  input logic Bin,
  output logic Diff,
  output logic Bout
);
  
  XOR2 xor1 (.a(A), .b(B), .y(Diff));
  XOR2 xor2 (.a(Diff), .b(Bin), .y(Diff));
  AND2 and1 (.a(~A), .b(B), .y(B1));
  AND2 and2 (.a(~A), .b(Bin), .y(B2));
  AND2 and3 (.a(B), .b(Bin), .y(B3));
  OR2 or1 (.a(B1), .b(B2), .y(Or1));
  OR2 or2 (.a(Or1), .b(B3), .y(Bout));
  
endmodule

cs223-2.srcs/sources_1/new/tb_full_substractor_test.sv
`timescale 1ns / 1ps
//////////////////////////////////////////////////////////////////////////////////
// Company: 
// Engineer: 
// 
// Create Date: 10.03.2024 16:07:04
// Design Name: 
// Module Name: tb_full_substractor_test
// Project Name: 
// Target Devices: 
// Tool Versions: 
// Description: 
// 
// Dependencies: 
// 
// Revision:
// Revision 0.01 - File Created
// Additional Comments:
// 
//////////////////////////////////////////////////////////////////////////////////

module tb_full_substractor_test();
// Inputs
  logic A, B, Bin;
  
  // Outputs
  logic Diff, Bout;
  
  // Instantiate the FullSubtractor module
  full_substractor_test uut (
    .A(A),
    .B(B),
    .Bin(Bin),
    .Diff(Diff),
    .Bout(Bout)
  );
  
  // Clock generation
  initial begin
    $dumpfile("tb_full_substractor_test.vcd");
    $dumpvars(0, tb_full_substractor_test);
    
    // Test case 1
    A = 0; B = 0; Bin = 0;
    #10;
    
    // Test case 2
    A = 1; B = 0; Bin = 0;
    #10;
    
    // Test case 3
    A = 0; B = 1; Bin = 0;
    #10;
    
    // Test case 4
    A = 1; B = 1; Bin = 0;
    #10;
    
    // Test case 5
    A = 0; B = 0; Bin = 1;
    #10;
    
    // Test case 6
    A = 1; B = 0; Bin = 1;
    #10;
    
    // Test case 7
    A = 0; B = 1; Bin = 1;
    #10;
    
    // Test case 8
    A = 1; B = 1; Bin = 1;
    #10;
    
    $finish;
  end

endmodule

cs223-2.sim/sim_1/behav/xsim/tb_full_substractor_test.vcd
$date
   Sun Mar 10 16:33:15 2024
$end

$version
  2023.2
  $dumpfile ("tb_full_substractor_test.vcd") 
$end

$timescale
  1ps
$end

$scope module tb_full_substractor_test $end
$var reg 1 ! A $end
$var reg 1 " B $end
$var reg 1 # Bin $end
$var reg 1 $ Diff $end
$var reg 1 % Bout $end
$scope module uut $end
$var wire 1 & A $end
$var wire 1 ' B $end
$var wire 1 ( Bin $end
$var reg 1 $ Diff $end
$var reg 1 % Bout $end
$var wire 1 ) B1 $end
$var wire 1 * B2 $end
$var wire 1 + B3 $end
$var wire 1 , Or1 $end
$scope module xor1 $end
$var wire 1 & a $end
$var wire 1 ' b $end
$var reg 1 $ y $end
$upscope $end
$scope module xor2 $end
$var wire 1 $ a $end
$var wire 1 ( b $end
$var reg 1 $ y $end
$upscope $end
$scope module and1 $end
$var wire 1 - a $end
$var wire 1 ' b $end
$var reg 1 . y $end
$upscope $end
$scope module and2 $end
$var wire 1 - a $end
$var wire 1 ( b $end
$var reg 1 / y $end
$upscope $end
$scope module and3 $end
$var wire 1 ' a $end
$var wire 1 ( b $end
$var reg 1 0 y $end
$upscope $end
$scope module or1 $end
$var wire 1 ) a $end
$var wire 1 * b $end
$var reg 1 1 y $end
$upscope $end
$scope module or2 $end
$var wire 1 , a $end
$var wire 1 + b $end
$var reg 1 % y $end
$upscope $end
$upscope $end
$upscope $end
$enddefinitions $end

#0
$dumpvars
0!
0"
0#
0$
0%
0&
0'
0(
0)
0*
0+
0,
1-
0.
0/
00
01
$end

#10000
1!
1$
1&
0-

#20000
0!
1"
1%
0&
1'
1)
1,
1-
1.
11

#30000
1!
0$
0%
1&
0)
0,
0-
0.
01

#40000
0!
0"
1#
1$
1%
0&
0'
1(
1*
1,
1-
1/
11

#50000
1!
0%
1&
0*
0,
0-
0/
01

#60000
0!
1"
1%
0&
1'
1)
1*
1+
1,
1-
1.
1/
10
11

#70000
1!
1$
1&
0)
0*
0,
0-
0.
0/
01
